cdc_ai_agent_client/__init__.py
cdc_ai_agent_client/client.py
cdc_ai_agent_client/integrations/__init__.py
cdc_ai_agent_client/integrations/cdc_ai_agent_api.py
cdc_ai_agent_client/integrations/cdc_ai_agent_interface.py
cdc_ai_agent_client-1.0.0b0.dist-info/LICENSE
cdc_ai_agent_client-1.0.0b0.dist-info/METADATA
cdc_ai_agent_client-1.0.0b0.dist-info/WHEEL
cdc_ai_agent_client-1.0.0b0.dist-info/entry_points.txt
cdc_ai_agent_client-1.0.0b0.dist-info/RECORD
