Metadata-Version: 2.1
Name: cdc-ai-agent-client
Version: 1.0.0b0
Summary: A python client to interact with the crypto.com AI agent service
Home-page: https://github.com/crypto-com/cdc-ai-agent-client-py
License: MIT
Keywords: agent,blockchain,crypto.com,AI,CDC
Author: Ric Arcifa
Author-email: ricardo.arcifa@crypto.com
Requires-Python: >=3.8.1,<4.0.0
Classifier: License :: OSI Approved :: MIT License
Classifier: Programming Language :: Python :: 3
Classifier: Programming Language :: Python :: 3.9
Classifier: Programming Language :: Python :: 3.10
Classifier: Programming Language :: Python :: 3.11
Classifier: Programming Language :: Python :: 3.12
Requires-Dist: requests (>=2.32.3,<3.0.0)
Project-URL: Documentation, https://github.com/crypto-com/cdc-ai-agent-client-py
Project-URL: Repository, https://github.com/crypto-com/cdc-ai-agent-client-py
